.empty
RELEASE_INFO.txt
generic_def.lib
install_common_functions.lib
setup.py
solaris_def.lib
workfloweng.py
cfg/wfeng.cfg
cfg/wfeng.ini
license/LICENSE.txt
license/NOTICE.txt
wfeng/__init__.py
wfeng/constants.py
wfeng/engformatter.py
wfeng/host.py
wfeng/inputmgr.py
wfeng/msgtask.py
wfeng/pluginmgr.py
wfeng/sequenceprocess.py
wfeng/status.py
wfeng/task.py
wfeng/taskcommons.py
wfeng/utils.py
wfeng/wfconfig.py
wfeng/wfini.py
wfeng/workflow.py
wfeng/workflowengine.py
wfeng/workflowsys.py
wfeng.egg-info/PKG-INFO
wfeng.egg-info/SOURCES.txt
wfeng.egg-info/dependency_links.txt
wfeng.egg-info/requires.txt
wfeng.egg-info/top_level.txt
xsd/hosts.xsd
xsd/workflow.xsd