Metadata-Version: 1.0
Name: wfeng
Version: 0.2
Summary: Ammeon workflow engine
Home-page: UNKNOWN
Author: Ammeon
Author-email: awe-support@ammeon.com, david.john.gee@ipengineer.net
License: Apache 2.0
Keywords: workflow engine orchestration
Platform: UNKNOWN
